ofautils/__init__.py
ofautils/engine.cpython-311-x86_64-linux-gnu.so
ofautils/g2pv.cpython-311-x86_64-linux-gnu.so
ofautils/triton.cpython-311-x86_64-linux-gnu.so
ofautils-0.1.0.dist-info/METADATA
ofautils-0.1.0.dist-info/WHEEL
ofautils-0.1.0.dist-info/RECORD
