Metadata-Version: 2.4
Name: ofautils
Version: 0.1.0
Summary: AIO Triton Utilities
Requires-Python: >=3.11
Requires-Dist: aiocache==0.11.1
Requires-Dist: aiohttp>=3.11.11
Requires-Dist: attrs>=24.3.0
Requires-Dist: fastapi>=0.115.6
Requires-Dist: fastcore>=1.7.27
Requires-Dist: librosa==0.11.0
Requires-Dist: loguru>=0.7.3
Requires-Dist: matplotlib==3.10.1
Requires-Dist: minio==5.0.10
Requires-Dist: numba==0.61.0
Requires-Dist: numpy==1.24.3
Requires-Dist: omegaconf>=2.3.0
Requires-Dist: pika==1.3.1
Requires-Dist: prometheus-client==0.13.1
Requires-Dist: psycopg2-binary==2.9.5
Requires-Dist: pybindgen>=0.22.1
Requires-Dist: pydantic>=2.10.4
Requires-Dist: pydub==0.25.1
Requires-Dist: pyjwt[crypto]==2.3.0
Requires-Dist: python-multipart>=0.0.20
Requires-Dist: pyyaml==6.0
Requires-Dist: scipy==1.10.0
Requires-Dist: setuptools>=75.6.0
Requires-Dist: sqlalchemy==1.4.45
Requires-Dist: starlette-exporter==0.13.0
Requires-Dist: tritonclient[grpc]>=2.52.0
Requires-Dist: uvicorn==0.24.0.post1
Requires-Dist: websockets>=15.0
